wserver_qdk/__init__.py
wserver_qdk/main.py
wserver_qdk/tools.py
wserver_qdk/tests/__init__.py
wserver_qdk/tests/main_test.py
wserver_qdk-0.0.2.dist-info/LICENSE
wserver_qdk-0.0.2.dist-info/METADATA
wserver_qdk-0.0.2.dist-info/WHEEL
wserver_qdk-0.0.2.dist-info/top_level.txt
wserver_qdk-0.0.2.dist-info/RECORD
