Metadata-Version: 2.1
Name: wserver-qdk
Version: 0.0.2
Summary: UNKNOWN
Home-page: UNKNOWN
Author: PunchyArchy
Author-email: ksmdrmvscthny@gmail.com
License: UNKNOWN
Platform: UNKNOWN
License-File: LICENSE
Requires-Dist: qodex-dk
